LICENSE.txt
MANIFEST.in
README.md
setup.cfg
setup.py
spotinst_sdk/__init__.py
spotinst_sdk/client.py
spotinst_sdk/session.py
spotinst_sdk/version.py
spotinst_sdk/clients/__init__.py
spotinst_sdk/clients/admin/__init__.py
spotinst_sdk/clients/elastigroup/__init__.py
spotinst_sdk/clients/functions/__init__.py
spotinst_sdk/clients/mcs/__init__.py
spotinst_sdk/clients/mlb/__init__.py
spotinst_sdk/clients/mrscaler/__init__.py
spotinst_sdk/clients/ocean/__init__.py
spotinst_sdk/clients/subscription/__init__.py
spotinst_sdk/models/__init__.py
spotinst_sdk/models/admin/__init__.py
spotinst_sdk/models/admin/user_mapping.py
spotinst_sdk/models/elastigroup/__init__.py
spotinst_sdk/models/elastigroup/aws/__init__.py
spotinst_sdk/models/elastigroup/aws/asg.py
spotinst_sdk/models/elastigroup/aws/deployment.py
spotinst_sdk/models/elastigroup/aws/deployment_action.py
spotinst_sdk/models/elastigroup/aws/stateful.py
spotinst_sdk/models/elastigroup/azure/__init__.py
spotinst_sdk/models/elastigroup/gcp/__init__.py
spotinst_sdk/models/elastigroup/gcp/gke.py
spotinst_sdk/models/functions/__init__.py
spotinst_sdk/models/mlb/__init__.py
spotinst_sdk/models/mrscaler/__init__.py
spotinst_sdk/models/mrscaler/aws/__init__.py
spotinst_sdk/models/ocean/__init__.py
spotinst_sdk/models/ocean/aws/__init__.py
spotinst_sdk/models/subscription/__init__.py
spotinst_sdk2_beta.egg-info/PKG-INFO
spotinst_sdk2_beta.egg-info/SOURCES.txt
spotinst_sdk2_beta.egg-info/dependency_links.txt
spotinst_sdk2_beta.egg-info/requires.txt
spotinst_sdk2_beta.egg-info/top_level.txt